odoo8_addon_account_direct_debit-8.0.2.1.0.99.dev16-py2.7-nspkg.pth
odoo8_addon_account_direct_debit-8.0.2.1.0.99.dev16.dist-info/DESCRIPTION.rst
odoo8_addon_account_direct_debit-8.0.2.1.0.99.dev16.dist-info/METADATA
odoo8_addon_account_direct_debit-8.0.2.1.0.99.dev16.dist-info/RECORD
odoo8_addon_account_direct_debit-8.0.2.1.0.99.dev16.dist-info/WHEEL
odoo8_addon_account_direct_debit-8.0.2.1.0.99.dev16.dist-info/metadata.json
odoo8_addon_account_direct_debit-8.0.2.1.0.99.dev16.dist-info/namespace_packages.txt
odoo8_addon_account_direct_debit-8.0.2.1.0.99.dev16.dist-info/top_level.txt
odoo_addons/account_direct_debit/README.rst
odoo_addons/account_direct_debit/__init__.py
odoo_addons/account_direct_debit/__openerp__.py
odoo_addons/account_direct_debit/data/account_payment_term.xml
odoo_addons/account_direct_debit/data/payment_mode_type.xml
odoo_addons/account_direct_debit/i18n/account_direct_debit.pot
odoo_addons/account_direct_debit/i18n/ca.po
odoo_addons/account_direct_debit/i18n/de.po
odoo_addons/account_direct_debit/i18n/es.po
odoo_addons/account_direct_debit/i18n/fi.po
odoo_addons/account_direct_debit/i18n/fr.po
odoo_addons/account_direct_debit/i18n/fr_CH.po
odoo_addons/account_direct_debit/i18n/id.po
odoo_addons/account_direct_debit/i18n/it.po
odoo_addons/account_direct_debit/i18n/nl.po
odoo_addons/account_direct_debit/i18n/pt_BR.po
odoo_addons/account_direct_debit/i18n/pt_PT.po
odoo_addons/account_direct_debit/i18n/ro_RO.po
odoo_addons/account_direct_debit/i18n/ru.po
odoo_addons/account_direct_debit/i18n/sl.po
odoo_addons/account_direct_debit/i18n/zh_CN.po
odoo_addons/account_direct_debit/models/__init__.py
odoo_addons/account_direct_debit/models/account_move_line.py
odoo_addons/account_direct_debit/models/payment_line.py
odoo_addons/account_direct_debit/static/description/icon.png
odoo_addons/account_direct_debit/views/account_payment.xml
odoo_addons/account_direct_debit/views/payment_mode.xml
odoo_addons/account_direct_debit/views/payment_mode_type.xml
odoo_addons/account_direct_debit/wizard/__init__.py
odoo_addons/account_direct_debit/wizard/payment_order_create.py
