Metadata-Version: 2.0
Name: odoo8-addon-account-direct-debit
Version: 8.0.2.1.0.99.dev16
Summary: Direct Debit
Home-page: https://github.com/OCA/bank-payment
Author: Therp BV, Smile, Odoo Community Association (OCA)
Author-email: support@odoo-community.org
License: AGPL-3
Platform: UNKNOWN
Classifier: Programming Language :: Python
Classifier: Framework :: Odoo
Classifier: License :: OSI Approved :: GNU Affero General Public License v3
Requires-Python: ~=2.7
Requires-Dist: odoo (<9.0a,>=8.0a)
Requires-Dist: odoo8-addon-account-banking-payment-export
